covid_alberta/__init__.py
covid_alberta/_nbdev.py
covid_alberta/analysis.py
covid_alberta/webscraper.py
temp/__init__.py
temp/albertaC19_webscraper.py
temp/alberta_stats.py
covid_alberta-0.0.4.dist-info/LICENSE
covid_alberta-0.0.4.dist-info/METADATA
covid_alberta-0.0.4.dist-info/WHEEL
covid_alberta-0.0.4.dist-info/entry_points.txt
covid_alberta-0.0.4.dist-info/top_level.txt
covid_alberta-0.0.4.dist-info/RECORD
