Metadata-Version: 2.1
Name: covid-alberta
Version: 0.0.4
Summary: This is a small package to look at some of the alberta specific covid data.
Home-page: https://github.com/tyleracorn/covid_alberta/tree/master/
Author: Tyler Acorn
Author-email: tyler.acorn@gmail.com
License: Apache Software License 2.0
Keywords: covid19 webscraper datacleaning
Platform: UNKNOWN
Classifier: Development Status :: 3 - Alpha
Classifier: Intended Audience :: Developers
Classifier: License :: OSI Approved :: Apache Software License
Classifier: Natural Language :: English
Classifier: Programming Language :: Python :: 3.6
Classifier: Programming Language :: Python :: 3.7
Classifier: Programming Language :: Python :: 3.8
Requires-Python: >=3.6
Requires-Dist: pandas
Requires-Dist: numpy
Requires-Dist: requests
Requires-Dist: bs4
